red_postgres/__init__.py
red_postgres/engine.py
red_postgres/errors.py
red_postgres-0.3.2.dist-info/LICENSE
red_postgres-0.3.2.dist-info/METADATA
red_postgres-0.3.2.dist-info/WHEEL
red_postgres-0.3.2.dist-info/top_level.txt
red_postgres-0.3.2.dist-info/RECORD
