Metadata-Version: 2.1
Name: red-postgres
Version: 0.3.2
Summary: Piccolo Postgres integration for Red
Author: Vertyco
Project-URL: Homepage, https://github.com/vertyco/red-postgres
Project-URL: Bug Tracker, https://github.com/vertyco/red-postgres/issues
Classifier: Programming Language :: Python :: 3
Classifier: License :: OSI Approved :: GNU General Public License v2 or later (GPLv2+)
Classifier: Operating System :: OS Independent
Requires-Python: >=3.11
License-File: LICENSE
